CalculosPacotes/__init__.py
CalculosPacotes/calculos.py
CalculosPacotes-0.0.2.dist-info/METADATA
CalculosPacotes-0.0.2.dist-info/WHEEL
CalculosPacotes-0.0.2.dist-info/top_level.txt
CalculosPacotes-0.0.2.dist-info/RECORD
