Metadata-Version: 2.1
Name: CalculosPacotes
Version: 0.0.2
Summary: Pacote em python
Author: Millena Lira
Author-email: millena.mp2@gmail.com
License: MIT
